{
    "correlationId": "12b7ac27",
    "title": "Unexpected Problem",
    "type": "https://api.weather.gov/problems/UnexpectedProblem",
    "status": 500,
    "detail": "An unexpected problem has occurred.",
    "instance": "https://api.weather.gov/requests/12b7ac27"
}{
    "correlationId": "12b7bff6",
    "title": "Unexpected Problem",
    "type": "https://api.weather.gov/problems/UnexpectedProblem",
    "status": 500,
    "detail": "An unexpected problem has occurred.",
    "instance": "https://api.weather.gov/requests/12b7bff6"
}{
    "correlationId": "12b7e5b0",
    "title": "Unexpected Problem",
    "type": "https://api.weather.gov/problems/UnexpectedProblem",
    "status": 500,
    "detail": "An unexpected problem has occurred.",
    "instance": "https://api.weather.gov/requests/12b7e5b0"
}{
    "correlationId": "21e76255",
    "title": "Unexpected Problem",
    "type": "https://api.weather.gov/problems/UnexpectedProblem",
    "status": 500,
    "detail": "An unexpected problem has occurred.",
    "instance": "https://api.weather.gov/requests/21e76255"
}{
    "correlationId": "5a9527a6",
    "title": "Unexpected Problem",
    "type": "https://api.weather.gov/problems/UnexpectedProblem",
    "status": 500,
    "detail": "An unexpected problem has occurred.",
    "instance": "https://api.weather.gov/requests/5a9527a6"
}{
    "correlationId": "21e8af6f",
    "title": "Unexpected Problem",
    "type": "https://api.weather.gov/problems/UnexpectedProblem",
    "status": 500,
    "detail": "An unexpected problem has occurred.",
    "instance": "https://api.weather.gov/requests/21e8af6f"
}