{
    "correlationId": "1d4a1845",
    "title": "Unexpected Problem",
    "type": "https://api.weather.gov/problems/UnexpectedProblem",
    "status": 500,
    "detail": "An unexpected problem has occurred.",
    "instance": "https://api.weather.gov/requests/1d4a1845"
}{
    "correlationId": "1b921299",
    "title": "Unexpected Problem",
    "type": "https://api.weather.gov/problems/UnexpectedProblem",
    "status": 500,
    "detail": "An unexpected problem has occurred.",
    "instance": "https://api.weather.gov/requests/1b921299"
}{
    "correlationId": "1deccd99",
    "title": "Unexpected Problem",
    "type": "https://api.weather.gov/problems/UnexpectedProblem",
    "status": 500,
    "detail": "An unexpected problem has occurred.",
    "instance": "https://api.weather.gov/requests/1deccd99"
}{
    "correlationId": "1decd347",
    "title": "Unexpected Problem",
    "type": "https://api.weather.gov/problems/UnexpectedProblem",
    "status": 500,
    "detail": "An unexpected problem has occurred.",
    "instance": "https://api.weather.gov/requests/1decd347"
}{
    "correlationId": "186078c2",
    "title": "Unexpected Problem",
    "type": "https://api.weather.gov/problems/UnexpectedProblem",
    "status": 500,
    "detail": "An unexpected problem has occurred.",
    "instance": "https://api.weather.gov/requests/186078c2"
}{
    "correlationId": "1d4ac890",
    "title": "Unexpected Problem",
    "type": "https://api.weather.gov/problems/UnexpectedProblem",
    "status": 500,
    "detail": "An unexpected problem has occurred.",
    "instance": "https://api.weather.gov/requests/1d4ac890"
}