{
    "correlationId": "37e7618d",
    "title": "Service Unavailable",
    "type": "https://api.weather.gov/problems/ServiceUnavailable",
    "status": 503,
    "detail": "An upstream data source is temporarily unavailable. Please try again later.",
    "instance": "https://api.weather.gov/requests/37e7618d"
}{
    "correlationId": "37e766c3",
    "title": "Service Unavailable",
    "type": "https://api.weather.gov/problems/ServiceUnavailable",
    "status": 503,
    "detail": "An upstream data source is temporarily unavailable. Please try again later.",
    "instance": "https://api.weather.gov/requests/37e766c3"
}{
    "correlationId": "37e7711f",
    "title": "Service Unavailable",
    "type": "https://api.weather.gov/problems/ServiceUnavailable",
    "status": 503,
    "detail": "An upstream data source is temporarily unavailable. Please try again later.",
    "instance": "https://api.weather.gov/requests/37e7711f"
}{
    "correlationId": "37b131fb",
    "title": "Service Unavailable",
    "type": "https://api.weather.gov/problems/ServiceUnavailable",
    "status": 503,
    "detail": "An upstream data source is temporarily unavailable. Please try again later.",
    "instance": "https://api.weather.gov/requests/37b131fb"
}{
    "correlationId": "39cd227b",
    "title": "Service Unavailable",
    "type": "https://api.weather.gov/problems/ServiceUnavailable",
    "status": 503,
    "detail": "An upstream data source is temporarily unavailable. Please try again later.",
    "instance": "https://api.weather.gov/requests/39cd227b"
}{
    "correlationId": "37e7fe71",
    "title": "Service Unavailable",
    "type": "https://api.weather.gov/problems/ServiceUnavailable",
    "status": 503,
    "detail": "An upstream data source is temporarily unavailable. Please try again later.",
    "instance": "https://api.weather.gov/requests/37e7fe71"
}