{
    "correlationId": "121a0b5a",
    "title": "Service Unavailable",
    "type": "https://api.weather.gov/problems/ServiceUnavailable",
    "status": 503,
    "detail": "An upstream data source is temporarily unavailable. Please try again later.",
    "instance": "https://api.weather.gov/requests/121a0b5a"
}{
    "correlationId": "6633720",
    "title": "Service Unavailable",
    "type": "https://api.weather.gov/problems/ServiceUnavailable",
    "status": 503,
    "detail": "An upstream data source is temporarily unavailable. Please try again later.",
    "instance": "https://api.weather.gov/requests/6633720"
}{
    "correlationId": "15b5c220",
    "title": "Service Unavailable",
    "type": "https://api.weather.gov/problems/ServiceUnavailable",
    "status": 503,
    "detail": "An upstream data source is temporarily unavailable. Please try again later.",
    "instance": "https://api.weather.gov/requests/15b5c220"
}{
    "correlationId": "6635185",
    "title": "Service Unavailable",
    "type": "https://api.weather.gov/problems/ServiceUnavailable",
    "status": 503,
    "detail": "An upstream data source is temporarily unavailable. Please try again later.",
    "instance": "https://api.weather.gov/requests/6635185"
}{
    "correlationId": "15bb86cb",
    "title": "Service Unavailable",
    "type": "https://api.weather.gov/problems/ServiceUnavailable",
    "status": 503,
    "detail": "An upstream data source is temporarily unavailable. Please try again later.",
    "instance": "https://api.weather.gov/requests/15bb86cb"
}{
    "correlationId": "3306328f",
    "title": "Service Unavailable",
    "type": "https://api.weather.gov/problems/ServiceUnavailable",
    "status": 503,
    "detail": "An upstream data source is temporarily unavailable. Please try again later.",
    "instance": "https://api.weather.gov/requests/3306328f"
}