{
    "correlationId": "14725590",
    "title": "Service Unavailable",
    "type": "https://api.weather.gov/problems/ServiceUnavailable",
    "status": 503,
    "detail": "An upstream data source is temporarily unavailable. Please try again later.",
    "instance": "https://api.weather.gov/requests/14725590"
}{
    "correlationId": "b112372",
    "title": "Service Unavailable",
    "type": "https://api.weather.gov/problems/ServiceUnavailable",
    "status": 503,
    "detail": "An upstream data source is temporarily unavailable. Please try again later.",
    "instance": "https://api.weather.gov/requests/b112372"
}{
    "correlationId": "b112d4b",
    "title": "Service Unavailable",
    "type": "https://api.weather.gov/problems/ServiceUnavailable",
    "status": 503,
    "detail": "An upstream data source is temporarily unavailable. Please try again later.",
    "instance": "https://api.weather.gov/requests/b112d4b"
}{
    "correlationId": "1724d25d",
    "title": "Service Unavailable",
    "type": "https://api.weather.gov/problems/ServiceUnavailable",
    "status": 503,
    "detail": "An upstream data source is temporarily unavailable. Please try again later.",
    "instance": "https://api.weather.gov/requests/1724d25d"
}{
    "correlationId": "1724f125",
    "title": "Service Unavailable",
    "type": "https://api.weather.gov/problems/ServiceUnavailable",
    "status": 503,
    "detail": "An upstream data source is temporarily unavailable. Please try again later.",
    "instance": "https://api.weather.gov/requests/1724f125"
}{
    "correlationId": "17f4f550",
    "title": "Unexpected Problem",
    "type": "https://api.weather.gov/problems/UnexpectedProblem",
    "status": 500,
    "detail": "An unexpected problem has occurred.",
    "instance": "https://api.weather.gov/requests/17f4f550"
}