{
    "correlationId": "23ec34e1",
    "title": "Service Unavailable",
    "type": "https://api.weather.gov/problems/ServiceUnavailable",
    "status": 503,
    "detail": "An upstream data source is temporarily unavailable. Please try again later.",
    "instance": "https://api.weather.gov/requests/23ec34e1"
}{
    "correlationId": "4724769d",
    "title": "Service Unavailable",
    "type": "https://api.weather.gov/problems/ServiceUnavailable",
    "status": 503,
    "detail": "An upstream data source is temporarily unavailable. Please try again later.",
    "instance": "https://api.weather.gov/requests/4724769d"
}{
    "correlationId": "169eeb18",
    "title": "Service Unavailable",
    "type": "https://api.weather.gov/problems/ServiceUnavailable",
    "status": 503,
    "detail": "An upstream data source is temporarily unavailable. Please try again later.",
    "instance": "https://api.weather.gov/requests/169eeb18"
}{
    "correlationId": "472477c7",
    "title": "Unexpected Problem",
    "type": "https://api.weather.gov/problems/UnexpectedProblem",
    "status": 500,
    "detail": "An unexpected problem has occurred.",
    "instance": "https://api.weather.gov/requests/472477c7"
}{
    "correlationId": "2e9f52ba",
    "title": "Unexpected Problem",
    "type": "https://api.weather.gov/problems/UnexpectedProblem",
    "status": 500,
    "detail": "An unexpected problem has occurred.",
    "instance": "https://api.weather.gov/requests/2e9f52ba"
}{
    "correlationId": "2e9f9129",
    "title": "Unexpected Problem",
    "type": "https://api.weather.gov/problems/UnexpectedProblem",
    "status": 500,
    "detail": "An unexpected problem has occurred.",
    "instance": "https://api.weather.gov/requests/2e9f9129"
}