{
    "correlationId": "ac1c7f5",
    "title": "Unexpected Problem",
    "type": "https://api.weather.gov/problems/UnexpectedProblem",
    "status": 500,
    "detail": "An unexpected problem has occurred. If this error continues, please contact support at nco.ops@noaa.gov.",
    "instance": "https://api.weather.gov/requests/ac1c7f5"
}{
    "correlationId": "b624fe9",
    "title": "Unexpected Problem",
    "type": "https://api.weather.gov/problems/UnexpectedProblem",
    "status": 500,
    "detail": "An unexpected problem has occurred. If this error continues, please contact support at nco.ops@noaa.gov.",
    "instance": "https://api.weather.gov/requests/b624fe9"
}{
    "correlationId": "b625c42",
    "title": "Unexpected Problem",
    "type": "https://api.weather.gov/problems/UnexpectedProblem",
    "status": 500,
    "detail": "An unexpected problem has occurred. If this error continues, please contact support at nco.ops@noaa.gov.",
    "instance": "https://api.weather.gov/requests/b625c42"
}{
    "correlationId": "cc88a1e",
    "title": "Unexpected Problem",
    "type": "https://api.weather.gov/problems/UnexpectedProblem",
    "status": 500,
    "detail": "An unexpected problem has occurred. If this error continues, please contact support at nco.ops@noaa.gov.",
    "instance": "https://api.weather.gov/requests/cc88a1e"
}{
    "correlationId": "c8ebb36",
    "title": "Unexpected Problem",
    "type": "https://api.weather.gov/problems/UnexpectedProblem",
    "status": 500,
    "detail": "An unexpected problem has occurred. If this error continues, please contact support at nco.ops@noaa.gov.",
    "instance": "https://api.weather.gov/requests/c8ebb36"
}{
    "correlationId": "d0ea2b5",
    "title": "Unexpected Problem",
    "type": "https://api.weather.gov/problems/UnexpectedProblem",
    "status": 500,
    "detail": "An unexpected problem has occurred. If this error continues, please contact support at nco.ops@noaa.gov.",
    "instance": "https://api.weather.gov/requests/d0ea2b5"
}