{
    "correlationId": "1d87dfa7",
    "title": "Unexpected Problem",
    "type": "https://api.weather.gov/problems/UnexpectedProblem",
    "status": 500,
    "detail": "An unexpected problem has occurred. If this error continues, please contact support at nco.ops@noaa.gov.",
    "instance": "https://api.weather.gov/requests/1d87dfa7"
}{
    "correlationId": "29f71e80",
    "title": "Unexpected Problem",
    "type": "https://api.weather.gov/problems/UnexpectedProblem",
    "status": 500,
    "detail": "An unexpected problem has occurred. If this error continues, please contact support at nco.ops@noaa.gov.",
    "instance": "https://api.weather.gov/requests/29f71e80"
}{
    "correlationId": "29f73293",
    "title": "Unexpected Problem",
    "type": "https://api.weather.gov/problems/UnexpectedProblem",
    "status": 500,
    "detail": "An unexpected problem has occurred. If this error continues, please contact support at nco.ops@noaa.gov.",
    "instance": "https://api.weather.gov/requests/29f73293"
}{
    "correlationId": "29f74a32",
    "title": "Unexpected Problem",
    "type": "https://api.weather.gov/problems/UnexpectedProblem",
    "status": 500,
    "detail": "An unexpected problem has occurred. If this error continues, please contact support at nco.ops@noaa.gov.",
    "instance": "https://api.weather.gov/requests/29f74a32"
}{
    "correlationId": "29f79f49",
    "title": "Unexpected Problem",
    "type": "https://api.weather.gov/problems/UnexpectedProblem",
    "status": 500,
    "detail": "An unexpected problem has occurred. If this error continues, please contact support at nco.ops@noaa.gov.",
    "instance": "https://api.weather.gov/requests/29f79f49"
}{
    "correlationId": "1d89ca23",
    "title": "Unexpected Problem",
    "type": "https://api.weather.gov/problems/UnexpectedProblem",
    "status": 500,
    "detail": "An unexpected problem has occurred. If this error continues, please contact support at nco.ops@noaa.gov.",
    "instance": "https://api.weather.gov/requests/1d89ca23"
}